import_git_files.py
import_git_files-0.1.0.dist-info/LICENSE
import_git_files-0.1.0.dist-info/METADATA
import_git_files-0.1.0.dist-info/WHEEL
import_git_files-0.1.0.dist-info/entry_points.txt
import_git_files-0.1.0.dist-info/top_level.txt
import_git_files-0.1.0.dist-info/RECORD
